sangwoo_cmd/__init__.py
sangwoo_cmd/cmd.py
sangwoo_cmd-0.1.1.dist-info/METADATA
sangwoo_cmd-0.1.1.dist-info/WHEEL
sangwoo_cmd-0.1.1.dist-info/entry_points.txt
sangwoo_cmd-0.1.1.dist-info/top_level.txt
sangwoo_cmd-0.1.1.dist-info/RECORD
