Metadata-Version: 2.1
Name: sangwoo_cmd
Version: 0.1.1
Summary: Default template for PDM package
Author-email: GITSangWoo <dogcenta@gmail.com>
License: MIT
Requires-Python: >=3.9
Requires-Dist: sangwoo-lotto >=0.2.0
